bbrc/__init__.py
bbrc/version.py
bbrc/data/ALFA_OPCIONAL_PLUS_FREESURFER6_99th_percentiles.xlsx
bbrc/data/ALFA_OPCIONAL_PLUS_FREESURFER6_HIRES_99th_percentiles.xlsx
bbrc/data/FreeSurferColorLUT.txt
bbrc/data/an_codes.json
bbrc/data/barcelonabeta.png
bbrc/data/freesurfer6_hires_items.json
bbrc/data/freesurfer6_items.json
bbrc/data/freesurfer7_items.json
bbrc/data/github.css
bbrc/data/logconf.ini
bbrc/data/scan_type_luts.json
bbrc/data/validation_rules.json
bbrc/data/versions.json
bbrc/data/protocol_validation/3D-pCASL_ALFA2-V2.json
bbrc/data/protocol_validation/AHEAD_Axial_DWI.json
bbrc/data/protocol_validation/AHEAD_Axial_T2-FLAIR.json
bbrc/data/protocol_validation/AHEAD_Axial_T2-Star.json
bbrc/data/protocol_validation/AHEAD_Sagittal_3D_Accelerated_MPRAGE.json
bbrc/data/protocol_validation/Axial_DTI_64.json
bbrc/data/protocol_validation/Axial_T2-Star.json
bbrc/data/protocol_validation/B0_DWI_100DIR.json
bbrc/data/protocol_validation/DTI_DEPPOST.json
bbrc/data/protocol_validation/DTI_HUGM.json
bbrc/data/protocol_validation/DWI_100DIR_8b0.json
bbrc/data/protocol_validation/DWI_ALFA1.json
bbrc/data/protocol_validation/DWI_MB2_PENSA.json
bbrc/data/protocol_validation/DWI_glymphatic.json
bbrc/data/protocol_validation/DelRec_QSM_ALFA2-V2.json
bbrc/data/protocol_validation/DelRec_SWIp.json
bbrc/data/protocol_validation/FLAIR.json
bbrc/data/protocol_validation/FLAIR_3D_1.5mm.json
bbrc/data/protocol_validation/FLAIR_ALFA1.json
bbrc/data/protocol_validation/HighResHippo_Scan.json
bbrc/data/protocol_validation/IR_ALFA1.json
bbrc/data/protocol_validation/IR_HUGM.json
bbrc/data/protocol_validation/LC_T1_TSE.json
bbrc/data/protocol_validation/M0_ASL.json
bbrc/data/protocol_validation/M0_TE-ASL_ALFA2-V3.json
bbrc/data/protocol_validation/M0_TR3700.json
bbrc/data/protocol_validation/M2DI.json
bbrc/data/protocol_validation/M2DI_ALFA2-V2.json
bbrc/data/protocol_validation/MATERNIDAD_SE-fMRI-AP.json
bbrc/data/protocol_validation/MATERNIDAD_SE-fMRI-PA.json
bbrc_validator-0.6.post1.dist-info/licenses/LICENSE
bbrc_validator-0.6.post1.dist-info/METADATA
bbrc_validator-0.6.post1.dist-info/WHEEL
bbrc_validator-0.6.post1.dist-info/top_level.txt
bbrc_validator-0.6.post1.dist-info/RECORD
