Metadata-Version: 2.4
Name: bbrc-validator
Version: 0.6.post1
Summary: Systematic sanity checks on imaging datasets within an XNAT environment
Home-page: https://gitlab.com/bbrc/xnat/bbrc-validator
Download-URL: https://gitlab.com/bbrc/xnat/bbrc-validator/-/archive/v0.6.post1/bbrc-validator-v0.6.post1.tar.gz
Author: Greg Operto, Jordi Huguet
Author-email: goperto@barcelonabeta.org
Classifier: Intended Audience :: Science/Research
Classifier: Intended Audience :: Developers
Classifier: Topic :: Scientific/Engineering
Classifier: Operating System :: Unix
Classifier: Programming Language :: Python :: 3.9
Classifier: Programming Language :: Python :: 3.10
License-File: LICENSE
Requires-Dist: coverage>=4.5
Requires-Dist: dateparser>=0.7
Requires-Dist: lxml>=4.3
Requires-Dist: Markdown>=3.0
Requires-Dist: nibabel>=2.3
Requires-Dist: nilearn>=0.5
Requires-Dist: pytest>=7.1
Requires-Dist: pytest-cov>=4.0
Requires-Dist: numpy>=1.16
Requires-Dist: pandas>=0.24
Requires-Dist: pdfkit>=0.6
Requires-Dist: pydicom<3.0,>=2.0
Requires-Dist: requests>=2.32
Requires-Dist: scikit-image>=0.14
Requires-Dist: scikit-learn>=1.5
Requires-Dist: scipy>=1.2
Requires-Dist: openpyxl>=3.1
Requires-Dist: bbrc-pyxnat>=1.6.3.dev1
Requires-Dist: pytz>=2019.1
Requires-Dist: nisnap==0.4.1
Requires-Dist: matplotlib<3.9,>=3.5
Requires-Dist: tqdm>=4.66
Requires-Dist: toml>=0.10.2
Requires-Dist: pdfkit>=0.6
Requires-Dist: urllib3<2
Dynamic: author
Dynamic: author-email
Dynamic: classifier
Dynamic: description
Dynamic: description-content-type
Dynamic: download-url
Dynamic: home-page
Dynamic: license-file
Dynamic: requires-dist
Dynamic: summary
